SyncVision/__init__.py
SyncVision/main.py
SyncVision/metrics.py
SyncVision/registration.py
tests/__init__.py
tests/test_main.py
SyncVision-1.1.3.dist-info/METADATA
SyncVision-1.1.3.dist-info/WHEEL
SyncVision-1.1.3.dist-info/top_level.txt
SyncVision-1.1.3.dist-info/RECORD
