Metadata-Version: 2.1
Name: SyncVision
Version: 1.1.3
Summary: A package for image registration using SIFT, ORB, and IntFeat.
Home-page: https://github.com/ashu1069/MoonMetaSync
Author: Ashutosh Kumar
Author-email: ak1825@rit.edu
Classifier: Programming Language :: Python :: 3
Classifier: License :: OSI Approved :: MIT License
Classifier: Operating System :: OS Independent
Requires-Python: >=3.6
Requires-Dist: numpy
Requires-Dist: pandas
Requires-Dist: matplotlib
Requires-Dist: opencv-python
Requires-Dist: scikit-learn
Requires-Dist: scikit-image
Requires-Dist: Pillow
